myrtio/__init__.py
myrtio/bytes.py
myrtio/constants.py
myrtio/message.py
myrtio/transport.py
myrtio-1.0.3.dist-info/METADATA
myrtio-1.0.3.dist-info/WHEEL
myrtio-1.0.3.dist-info/top_level.txt
myrtio-1.0.3.dist-info/RECORD
